.DS_Store
ssnmf/__init__.py
ssnmf/evaluation.py
ssnmf/example.py
ssnmf/ssnmf.py
ssnmf/ssnmf_numpy.py
ssnmf/ssnmf_pytorch.py
ssnmf/visualization.py
ssnmf-1.0.3.dist-info/LICENSE
ssnmf-1.0.3.dist-info/METADATA
ssnmf-1.0.3.dist-info/WHEEL
ssnmf-1.0.3.dist-info/top_level.txt
ssnmf-1.0.3.dist-info/RECORD
