Metadata-Version: 2.1
Name: ssnmf
Version: 1.0.3
Summary: SSNMF contains class for (SS)NMF model and several multiplicative update methods to train different models.
Home-page: https://github.com/jamiehadd/ssnmf
Author: Jamie Haddock
Author-email: jhaddock@math.ucla.edu
License: MIT
Keywords: ssnmf
Platform: UNKNOWN
Classifier: Development Status :: 2 - Pre-Alpha
Classifier: Intended Audience :: Science/Research 
Classifier: License :: OSI Approved :: MIT License
Classifier: Natural Language :: English
Classifier: Programming Language :: Python
Classifier: Programming Language :: Python :: 3
Classifier: Programming Language :: Python :: 3 :: Only
Classifier: Programming Language :: Python :: 3.5
Classifier: Programming Language :: Python :: 3.6
Classifier: Programming Language :: Python :: 3.7
Classifier: Programming Language :: Python :: 3.8
Classifier: Topic :: Scientific/Engineering
Requires-Python: >=3.5
Requires-Dist: numpy
Provides-Extra: all
Requires-Dist: numpy ; extra == 'all'
Requires-Dist: scipy ; extra == 'all'
Requires-Dist: pytest ; extra == 'all'
Requires-Dist: bump2version (>=1.0.3) ; extra == 'all'
Requires-Dist: ipython (>=7.5.0) ; extra == 'all'
Requires-Dist: twine (>=1.13.0) ; extra == 'all'
Requires-Dist: wheel (>=0.33.1) ; extra == 'all'
Requires-Dist: tox (>=3.15.0) ; extra == 'all'
Provides-Extra: dev
Requires-Dist: scipy ; extra == 'dev'
Requires-Dist: pytest ; extra == 'dev'
Requires-Dist: bump2version (>=1.0.3) ; extra == 'dev'
Requires-Dist: ipython (>=7.5.0) ; extra == 'dev'
Requires-Dist: twine (>=1.13.0) ; extra == 'dev'
Requires-Dist: wheel (>=0.33.1) ; extra == 'dev'
Requires-Dist: tox (>=3.15.0) ; extra == 'dev'
Provides-Extra: docs
Provides-Extra: setup
Provides-Extra: test
Requires-Dist: scipy ; extra == 'test'
Requires-Dist: pytest ; extra == 'test'
